keaml/__init__.py
keaml/client.py
keaml/inference.py
keaml-0.1.3.dist-info/METADATA
keaml-0.1.3.dist-info/WHEEL
keaml-0.1.3.dist-info/top_level.txt
keaml-0.1.3.dist-info/RECORD
