Metadata-Version: 2.1
Name: keaml
Version: 0.1.3
Summary: KeaML Python SDK
Author: Gabriel Obaldia
Author-email: support@keaml.com
Requires-Dist: joblib ==1.3.2
